kinto_portier/__init__.py
kinto_portier/authentication.py
kinto_portier/crypto.py
kinto_portier/utils.py
kinto_portier/views.py
kinto_portier/tests/__init__.py
kinto_portier/tests/test_authentication.py
kinto_portier/tests/test_includeme.py
kinto_portier/tests/test_views.py
kinto_portier-0.4.0.dist-info/DESCRIPTION.rst
kinto_portier-0.4.0.dist-info/METADATA
kinto_portier-0.4.0.dist-info/RECORD
kinto_portier-0.4.0.dist-info/WHEEL
kinto_portier-0.4.0.dist-info/metadata.json
kinto_portier-0.4.0.dist-info/top_level.txt
