Metadata-Version: 2.0
Name: kinto-portier
Version: 0.4.0
Summary: Portier authentication support in Kinto
Home-page: https://github.com/Kinto/kinto-portier
Author: Mozilla Services
Author-email: services-dev@mozilla.com
License: Apache License (2.0)
Keywords: web services
Platform: UNKNOWN
Classifier: Programming Language :: Python
Classifier: Programming Language :: Python :: 2.7
Classifier: Programming Language :: Python :: 3.4
Classifier: Programming Language :: Python :: 3.5
Classifier: Topic :: Internet :: WWW/HTTP
Classifier: Topic :: Internet :: WWW/HTTP :: WSGI :: Application
Classifier: License :: OSI Approved :: Apache Software License
Requires-Dist: PyJWT
Requires-Dist: cryptography
Requires-Dist: kinto
Requires-Dist: portier-python
Requires-Dist: requests
